algonaut/__init__.py
algonaut/api/__init__.py
algonaut/api/app.py
algonaut/api/resource.py
algonaut/api/uwsgi.py
algonaut/api/decorators/__init__.py
algonaut/api/v1/__init__.py
algonaut/api/v1/routes.py
algonaut/api/v1/forms/__init__.py
algonaut/api/v1/forms/validators.py
algonaut/api/v1/resources/__init__.py
algonaut/cli/__init__.py
algonaut/cli/api.py
algonaut/cli/db.py
algonaut/cli/main.py
algonaut/cli/worker.py
algonaut/models/__init__.py
algonaut/models/base.py
algonaut/plugins/__init__.py
algonaut/plugins/example/__init__.py
algonaut/plugins/example/setup.py
algonaut/plugins/example/models/__init__.py
algonaut/settings/__init__.py
algonaut/settings/base.py
algonaut/tests/__init__.py
algonaut/tests/helpers.py
algonaut/tests/fixtures/__init__.py
algonaut/utils/__init__.py
algonaut/utils/celery.py
algonaut/utils/migrations.py
algonaut/utils/regex.py
algonaut/utils/settings.py
algonaut/utils/email/__init__.py
algonaut/utils/email/jinja.py
algonaut/utils/email/send.py
algonaut/utils/forms/__init__.py
algonaut/utils/forms/field.py
algonaut/utils/forms/form.py
algonaut/utils/forms/validators.py
algonaut/utils/helpers/__init__.py
algonaut/utils/helpers/celery.py
algonaut/worker/__init__.py
algonaut/worker/run.py
algonaut/worker/models/__init__.py
algonaut/worker/models/base.py
algonaut/worker/models/task.py
algonaut/worker/tasks/__init__.py
algonaut/worker/tasks/ping.py
algonaut-0.0.1.dist-info/METADATA
algonaut-0.0.1.dist-info/WHEEL
algonaut-0.0.1.dist-info/entry_points.txt
algonaut-0.0.1.dist-info/top_level.txt
algonaut-0.0.1.dist-info/RECORD
