Metadata-Version: 2.1
Name: algonaut
Version: 0.0.1
Summary: The API toolkit for Algoneer.
Home-page: https://github.com/algoneer/algonaut
Author: Andreas Dewes
Author-email: andreas.dewes@algoneer.org
License: GNU Affero General Public License - Version 3 (AGPL-3)
Platform: UNKNOWN
Requires-Python: >=3
Requires-Dist: psycopg2-binary (==2.8.3)
Requires-Dist: celery (==4.2.1)
Requires-Dist: cryptography (==2.7)
Requires-Dist: click (==6.7)
Requires-Dist: Flask (==1.0.2)
Requires-Dist: pytz (==2018.7)
Requires-Dist: PyYAML (==3.12)
Requires-Dist: requests (==2.18.4)
Requires-Dist: SQLAlchemy (==1.2.7)
Requires-Dist: SQLAlchemy-Utils (==0.33.3)
